py3seed/__init__.py
py3seed/__main__.py
py3seed/admin.py
py3seed/cachesupport.py
py3seed/error.py
py3seed/ext.py
py3seed/inflection.py
py3seed/log.py
py3seed/merge3.py
py3seed/model.py
py3seed/mongosupport.py
py3seed/utils.py
py3seed/websupport.py
py3seed/commands/__init__.py
py3seed/commands/gen.py
py3seed-0.7.1.dist-info/LICENSE
py3seed-0.7.1.dist-info/METADATA
py3seed-0.7.1.dist-info/WHEEL
py3seed-0.7.1.dist-info/entry_points.txt
py3seed-0.7.1.dist-info/top_level.txt
py3seed-0.7.1.dist-info/RECORD
