Metadata-Version: 2.1
Name: py3seed
Version: 0.7.1
Summary: A package that bootstraps your project by simple data models definition and auto api and user interface generation
Home-page: https://github.com/okosioc/pyseed
Author: Samuel Feng
Author-email: okosioc@gmail.com
Project-URL: Bug Tracker, https://github.com/okosioc/pyseed/issues
Classifier: Programming Language :: Python :: 3
Classifier: License :: OSI Approved :: MIT License
Classifier: Operating System :: OS Independent
Requires-Python: >=3.8
License-File: LICENSE
Requires-Dist: importlib-metadata>=4.4
Requires-Dist: pymongo<4.9
Requires-Dist: werkzeug
Requires-Dist: Flask
